rwkv_simple/__init__.py
rwkv_simple/rwkv.py
rwkv_simple/tokenizer.py
rwkv_simple/cuda/wkv6_cuda.cu
rwkv_simple/cuda/wkv6_op.cpp
rwkv_simple/vocab/rwkv_vocab_v20230424.txt
rwkv_simple-0.1.1.dist-info/LICENSE
rwkv_simple-0.1.1.dist-info/METADATA
rwkv_simple-0.1.1.dist-info/WHEEL
rwkv_simple-0.1.1.dist-info/top_level.txt
rwkv_simple-0.1.1.dist-info/RECORD
