Metadata-Version: 2.1
Name: rwkv_simple
Version: 0.1.1
Summary: Easy-to-use RWKV-6 (x060) implementation
Author-email: Ronsor Labs <ronsor@ronsor.com>
Project-URL: Homepage, https://github.com/ronsor/rwkv-simple
Project-URL: Issues, https://github.com/ronsor/rwkv-simple/issues
Classifier: Programming Language :: Python :: 3
Classifier: License :: OSI Approved :: Apache Software License
Classifier: Operating System :: OS Independent
Requires-Python: >=3.10
License-File: LICENSE
Requires-Dist: torch >=2.1.0
Requires-Dist: einops >=0.7.0
Provides-Extra: fla
Requires-Dist: fla ; extra == 'fla'
